basket/__init__.py
basket/cli.py
basket/basket_config/__init__.py
basket/basket_config/auths_config.py
basket/basket_config/maas_config.py
basket/openai_util/__init__.py
basket/openai_util/openai_util.py
orchard_basket-0.1.1.dist-info/LICENSE
orchard_basket-0.1.1.dist-info/METADATA
orchard_basket-0.1.1.dist-info/WHEEL
orchard_basket-0.1.1.dist-info/entry_points.txt
orchard_basket-0.1.1.dist-info/top_level.txt
orchard_basket-0.1.1.dist-info/RECORD
