Metadata-Version: 2.1
Name: orchard-basket
Version: 0.1.1
Summary: Basket is the essential toolkit for seamless MaaS integration.
Home-page: https://github.com/OrchardUniverse/basket
Author: Orchard Universe
Classifier: Programming Language :: Python :: 3
Classifier: License :: OSI Approved :: MIT License
Classifier: Operating System :: OS Independent
Requires-Python: >=3.6
License-File: LICENSE
Requires-Dist: openai
Requires-Dist: pyyaml
Requires-Dist: tabulate
Requires-Dist: coloredlogs
Requires-Dist: httpx[socks]
